[
  {"id": "nordvpn-vs-protonvpn", "slug": "nordvpn-vs-protonvpn", "providers": ["nordvpn", "protonvpn"], "title": "NordVPN vs Proton VPN (2026): Security vs Privacy"},
  {"id": "nordvpn-vs-fastestvpn", "slug": "nordvpn-vs-fastestvpn", "providers": ["nordvpn", "fastestvpn"], "title": "NordVPN vs FastestVPN (2026): Premium vs Budget"},
  {"id": "protonvpn-vs-fastestvpn", "slug": "protonvpn-vs-fastestvpn", "providers": ["protonvpn", "fastestvpn"], "title": "Proton VPN vs FastestVPN (2026): Privacy vs Price"},
  {"id": "nordvpn-vs-surfshark", "slug": "nordvpn-vs-surfshark", "providers": ["nordvpn", "surfshark"], "title": "NordVPN vs Surfshark (2026): Speed vs Unlimited Devices"},
  {"id": "surfshark-vs-protonvpn", "slug": "surfshark-vs-protonvpn", "providers": ["surfshark", "protonvpn"], "title": "Surfshark vs Proton VPN (2026): Devices vs Privacy"},
  {"id": "surfshark-vs-fastestvpn", "slug": "surfshark-vs-fastestvpn", "providers": ["surfshark", "fastestvpn"], "title": "Surfshark vs FastestVPN (2026): Unlimited Devices vs Lifetime Deal"},
  {"id": "nordvpn-vs-expressvpn", "slug": "nordvpn-vs-expressvpn", "providers": ["nordvpn", "expressvpn"], "title": "NordVPN vs ExpressVPN (2026): Which Is Actually Better?"},
  {"id": "surfshark-vs-expressvpn", "slug": "surfshark-vs-expressvpn", "providers": ["surfshark", "expressvpn"], "title": "Surfshark vs ExpressVPN (2026): Budget vs Premium"},
  {"id": "nordvpn-vs-cyberghost", "slug": "nordvpn-vs-cyberghost", "providers": ["nordvpn", "cyberghost"], "title": "NordVPN vs CyberGhost (2026): Speed vs Server Count"},
  {"id": "surfshark-vs-cyberghost", "slug": "surfshark-vs-cyberghost", "providers": ["surfshark", "cyberghost"], "title": "Surfshark vs CyberGhost (2026): Unlimited Devices vs Streaming"},
  {"id": "expressvpn-vs-cyberghost", "slug": "expressvpn-vs-cyberghost", "providers": ["expressvpn", "cyberghost"], "title": "ExpressVPN vs CyberGhost (2026): Premium vs Value"},
  {"id": "ipvanish-vs-nordvpn", "slug": "ipvanish-vs-nordvpn", "providers": ["ipvanish", "nordvpn"], "title": "IPVanish vs NordVPN (2026): Streaming vs Overall"},
  {"id": "ipvanish-vs-surfshark", "slug": "ipvanish-vs-surfshark", "providers": ["ipvanish", "surfshark"], "title": "IPVanish vs Surfshark (2026): Streaming vs Unlimited Devices"},
  {"id": "ipvanish-vs-protonvpn", "slug": "ipvanish-vs-protonvpn", "providers": ["ipvanish", "protonvpn"], "title": "IPVanish vs Proton VPN (2026): Streaming vs Privacy"},
  {"id": "ipvanish-vs-fastestvpn", "slug": "ipvanish-vs-fastestvpn", "providers": ["ipvanish", "fastestvpn"], "title": "IPVanish vs FastestVPN (2026): Streaming vs Budget"}
]
